{
  "todoList": [
    {
      "id": "1",
      "title": "Check Mails",
      "description": "Check if there are any new mails.",
      "dateCreated": "1/10/15",
      "completed": false,
      "dateCompleted": ""
    },
    {
      "id": "2",
      "title": "Pay rent",
      "description": "Check for the utilities bills as well.",
      "dateCreated": "1/10/15",
      "completed": false,
      "dateCompleted": ""
    },
    {
      "id": "3",
      "title": "Pay tution fee",
      "description": "Check if the CTA pass fee is included.",
      "dateCreated": "11/10/15",
      "completed": false,
      "dateCompleted": ""
    },
    {
      "id": "0.04575861616177024",
      "title": "a",
      "description": "a",
      "dateCreated": "10/18/2021",
      "completed": false,
      "dateCompleted": ""
    }
  ],
  "users": [
    {
      "id": 1,
      "username": "testuser",
      "password": "badpassword"
    },
    {
      "id": 2,
      "username": "anam",
      "password": "anam"
    }
  ]
}